pysolid/grid.py
pysolid/solid.for
pysolid/point.py
pysolid/solid.cpython-310-x86_64-linux-gnu.so
pysolid/__init__.py
pysolid.libs/libgcc_s-a3a07607.so.1
pysolid.libs/libgfortran-e686bd2c.so.5.0.0
pysolid.libs/libquadmath-9b5eedf9.so.0.0.0
pysolid-0.3.3.dist-info/WHEEL
pysolid-0.3.3.dist-info/RECORD
pysolid-0.3.3.dist-info/METADATA
pysolid-0.3.3.dist-info/licenses/LICENSE
