Metadata-Version: 2.1
Name: pysolid
Version: 0.3.3
Summary: A Python wrapper for solid to compute solid Earth tides
Keywords: solid Earth tides,deformation,geodesy,geophysics
Author: Dennis Milbert
Author-Email: Zhang Yunjun <yunjunz@outlook.com>
License: GPL-3.0-or-later
Classifier: Development Status :: 4 - Beta
Classifier: Intended Audience :: Science/Research
Classifier: Topic :: Scientific/Engineering
Classifier: License :: OSI Approved :: GNU General Public License v3 or later (GPLv3+)
Classifier: Operating System :: OS Independent
Classifier: Programming Language :: Python :: 3
Project-URL: Homepage, https://github.com/insarlab/PySolid
Project-URL: Bug tracker, https://github.com/insarlab/PySolid/issues
Requires-Python: >=3.8
Requires-Dist: numpy
Requires-Dist: scipy
